[{"nom_planification":"Normal","Id":"jee-uniq-1-027n","semaine":[{"jour":"Lundi","periodes":[{"Type_periode":"heure_fixe","Debut_periode":"00:00","Id":"7405"},{"Type_periode":"heure_fixe","Debut_periode":"07:30","Id":"7403"},{"Type_periode":"coucher","Debut_periode":"","Id":"7405"}]},{"jour":"Mardi","periodes":[{"Type_periode":"heure_fixe","Debut_periode":"00:00","Id":"7405"},{"Type_periode":"heure_fixe","Debut_periode":"07:30","Id":"7403"},{"Type_periode":"coucher","Debut_periode":"","Id":"7405"}]},{"jour":"Mercredi","periodes":[{"Type_periode":"heure_fixe","Debut_periode":"00:00","Id":"7405"},{"Type_periode":"heure_fixe","Debut_periode":"09:30","Id":"7403"},{"Type_periode":"coucher","Debut_periode":"","Id":"7405"}]},{"jour":"Jeudi","periodes":[{"Type_periode":"heure_fixe","Debut_periode":"00:00","Id":"7405"},{"Type_periode":"heure_fixe","Debut_periode":"07:30","Id":"7403"},{"Type_periode":"coucher","Debut_periode":"","Id":"7405"}]},{"jour":"Vendredi","periodes":[{"Type_periode":"heure_fixe","Debut_periode":"00:00","Id":"7405"},{"Type_periode":"heure_fixe","Debut_periode":"07:30","Id":"7403"},{"Type_periode":"coucher","Debut_periode":"","Id":"7405"}]},{"jour":"Samedi","periodes":[{"Type_periode":"heure_fixe","Debut_periode":"00:00","Id":"7405"},{"Type_periode":"heure_fixe","Debut_periode":"10:00","Id":"7403"},{"Type_periode":"coucher","Debut_periode":"","Id":"7405"}]},{"jour":"Dimanche","periodes":[{"Type_periode":"heure_fixe","Debut_periode":"00:00","Id":"7405"},{"Type_periode":"heure_fixe","Debut_periode":"10:00","Id":"7403"},{"Type_periode":"coucher","Debut_periode":"","Id":"7405"}]}]},{"nom_planification":"Vacances","Id":"jee-uniq-0-r66oi","semaine":[{"jour":"Lundi","periodes":[{"Type_periode":"heure_fixe","Debut_periode":"00:00","Id":"7405"},{"Type_periode":"heure_fixe","Debut_periode":"10:00","Id":"7403"},{"Type_periode":"coucher","Debut_periode":"","Id":"7405"}]},{"jour":"Mardi","periodes":[{"Type_periode":"heure_fixe","Debut_periode":"00:00","Id":"7405"},{"Type_periode":"heure_fixe","Debut_periode":"10:00","Id":"7403"},{"Type_periode":"coucher","Debut_periode":"","Id":"7405"}]},{"jour":"Mercredi","periodes":[{"Type_periode":"heure_fixe","Debut_periode":"00:00","Id":"7405"},{"Type_periode":"heure_fixe","Debut_periode":"10:00","Id":"7403"},{"Type_periode":"coucher","Debut_periode":"","Id":"7405"}]},{"jour":"Jeudi","periodes":[{"Type_periode":"heure_fixe","Debut_periode":"00:00","Id":"7405"},{"Type_periode":"heure_fixe","Debut_periode":"10:00","Id":"7403"},{"Type_periode":"coucher","Debut_periode":"","Id":"7405"}]},{"jour":"Vendredi","periodes":[{"Type_periode":"heure_fixe","Debut_periode":"00:00","Id":"7405"},{"Type_periode":"heure_fixe","Debut_periode":"10:00","Id":"7403"},{"Type_periode":"coucher","Debut_periode":"","Id":"7405"}]},{"jour":"Samedi","periodes":[{"Type_periode":"heure_fixe","Debut_periode":"00:00","Id":"7405"},{"Type_periode":"heure_fixe","Debut_periode":"10:00","Id":"7403"},{"Type_periode":"coucher","Debut_periode":"","Id":"7405"}]},{"jour":"Dimanche","periodes":[{"Type_periode":"heure_fixe","Debut_periode":"00:00","Id":"7405"},{"Type_periode":"heure_fixe","Debut_periode":"10:00","Id":"7403"},{"Type_periode":"coucher","Debut_periode":"","Id":"7405"}]}]}]